divider.sv
module divider #(parameter M = 32) (
    input wire [M-1:0] A,
    input wire [M-1:0] B,
    output reg [M-1:0] quotient,
    output reg [M-1:0] remainder,
    output reg error
);

    integer i;
    reg [M-1:0] negated_B;
    reg [M-1:0] temp_remainder;

    always @(*) begin
        negated_B = ~B; // Negacja bitowa B
        quotient = 0;
        temp_remainder = 0;
        error = 0;

        // Sprawdzenie dzielenia przez zero
        if (negated_B == 0) begin
            error = 1;
            quotient = 'bx; // stan nieokreślony
            remainder = 'bx; 
        end else begin
            for (i = M-1; i >= 0; i = i - 1) begin
                temp_remainder = temp_remainder << 1;
                temp_remainder[0] = A[i];

                if (temp_remainder >= negated_B) begin
                    temp_remainder = temp_remainder - negated_B;
                    quotient[i] = 1;
                end
            end
            remainder = temp_remainder;
        end
    end
endmodule

sync_arith_unit_29.sv
`include "divider.sv"

`timescale 1ns / 1ps

module sync_arith_unit_29 #(parameter M = 32) (
    input wire [M-1:0] iarg_A, 
    input wire [M-1:0] iarg_B, 
    input wire [3:0] iop, 
    input wire clk, 
    input wire i_reset, 
    output reg [M-1:0] o_result,
    output reg [3:0] o_status
);

    localparam OP_BITWISE_SHIFT = 4'b0000; 
    localparam OP_COMPARE_AS = 4'b0001; 
    localparam OP_DIVIDE = 4'b0010; 
    localparam OP_ZM_TO_U2 = 4'b0011; 

    localparam ERROR = 3; 
    localparam NOT_EVEN_1 = 2; 
    localparam ZEROS = 1; 
    localparam OVERFLOW = 0; 

    wire [M-1:0] quotient, remainder; // Iloraz i reszta z dzielenia
    wire division_error; // Sygnał błędu podczas dzielenia
    divider #(.M(M)) div_unit (
        .A(iarg_A),
        .B(~iarg_B),
        .quotient(quotient),
        .remainder(remainder),
        .error(division_error)
    );

    always @(posedge clk or negedge i_reset) begin
        if (!i_reset) begin
            o_result <= 0;
            o_status <= 0;
        end else begin
            o_status <= 4'b0000; // Resetuj status 
            case (iop)
                OP_BITWISE_SHIFT: begin
                    if (iarg_B >= M) begin
                        o_result <= 0;
                        o_status[OVERFLOW] <= 1'b1;
                    end else begin
                        o_result <= iarg_A >> iarg_B;
                    end
                    o_status[ZEROS] <= (o_result == 0);
                    o_status[NOT_EVEN_1] <= (^o_result);
                end
                OP_COMPARE_AS: begin
                    // Porównanie A <= ~B w kodzie ZM
                    if (iarg_A[M-1] == iarg_B[M-1]) begin
                        // Liczby mają taki sam znak
                        o_result <= (iarg_A < iarg_B) ? 1'b1 : 1'b0;
                    end else begin
                        // Liczby mają przeciwne znaki
                        o_result <= iarg_A[M-1] ? 1'b0 : 1'b1;
                    end
                end
                OP_DIVIDE: begin
                    if (division_error) begin
                        o_status <= 4'b1000; // Błąd
                        o_result <= {(M){1'bx}}; // Wynik nieokreślony
                    end else begin
                        o_result <= quotient;
                        o_status <= 4'b0000;
                    end
                end
                OP_ZM_TO_U2: begin
                    if (iarg_A[M-1]) begin
                        if (iarg_A == {1'b1, {(M-1){1'b0}}}) begin
                            o_result <= {(M){1'bx}}; // Wynik nieokreślony
                            o_status[ERROR] <= 1'b1; // Błąd
                        end else begin
                            o_result <= {1'b1, ~iarg_A[M-2:0] + 1'b1};
                        end
                    end else begin
                        o_result <= iarg_A; // Liczba dodatnia pozostaje bez zmian
                    end
                end
                default: begin
                    o_status[ERROR] <= 1'b1;
                end
            endcase

            o_status[ZEROS] <= (o_result == 0);
            o_status[NOT_EVEN_1] <= (^o_result) & ~o_status[ERROR];
        end
    end
endmodule

sync_arith_unit_29_tb.sv
`include "sync_arith_unit_29.sv"

`timescale 1ns / 1ps

module test_sync_arith_unit_29;

    parameter M = 32;
    reg [M-1:0] iarg_A;
    reg [M-1:0] iarg_B;
    reg [3:0] iop;
    reg [31:0] time_counter;
    reg [31:0] time_limit = 1000; // Set the time limit for simulation

    initial begin
        $dumpfile("waveform.vcd");
        $dumpvars(0, test_sync_arith_unit_29);

        clk = 0;
        i_reset = 0;
        time_counter = 0;

        while (time_counter < time_limit) begin
            #5; // Wait for 5 time units
            time_counter = time_counter + 5;
        end

        $finish;
    end
    reg clk;
    reg i_reset;
    wire [M-1:0] o_result;
    wire [3:0] o_status;

    localparam OP_BITWISE_SHIFT = 4'b0000;
    localparam OP_COMPARE_AS = 4'b0001;
    localparam OP_DIVIDE = 4'b0010;
    localparam OP_ZM_TO_U2 = 4'b0011;

    sync_arith_unit_29 #(.M(M)) uut (
        .iarg_A(iarg_A),
        .iarg_B(iarg_B),
        .iop(iop),
        .clk(clk),
        .i_reset(i_reset),
        .o_result(o_result),
        .o_status(o_status)
    );

    initial begin
        clk = 0;
        forever #10 clk = ~clk;
    end

    initial begin
        i_reset = 0;
        #20;
        i_reset = 1;
        #20;

        perform_shift_tests();
        perform_compare_as_tests();
        perform_divide_tests();
        perform_zm_to_u2_tests();
        perform_flag_status();

        $finish;
    end

    // Testy dla OP_BITWISE_SHIFT
    task perform_shift_tests;
        begin
            performTest(32'hA5A5A5A5, 0, OP_BITWISE_SHIFT);
            performTest(32'hA5A5A5A5, 1, OP_BITWISE_SHIFT);
            performTest(32'hA5A5A5A5, 2, OP_BITWISE_SHIFT);
            performTest(32'hA5A5A5A5, 3, OP_BITWISE_SHIFT);
            performTest(32'hA5A5A5A5, 4, OP_BITWISE_SHIFT);
            performTest(32'hA5A5A5A5, 31, OP_BITWISE_SHIFT);
            performTest(32'hA5A5A5A5, 32, OP_BITWISE_SHIFT);
            performTest(32'hA5A5A5A5, 33, OP_BITWISE_SHIFT);
        end
    endtask

    // Testy dla OP_COMPARE_AS
    task perform_compare_as_tests;
        begin
            performTest(32'h00000001, 32'hFFFFFFFF, OP_COMPARE_AS);
            performTest(32'h00000002, 32'hFFFFFFFE, OP_COMPARE_AS);
            performTest(32'h00000003, 32'hFFFFFFFD, OP_COMPARE_AS);
            performTest(32'h00000004, 32'hFFFFFFFC, OP_COMPARE_AS);
            performTest(32'h00000005, 32'hFFFFFFFB, OP_COMPARE_AS);
            performTest(32'h7FFFFFFF, 32'h80000000, OP_COMPARE_AS);
            performTest(32'hFFFFFFFF, 32'h7FFFFFFF, OP_COMPARE_AS);
        end
    endtask

    // Testy dla OP_DIVIDE
    task perform_divide_tests;
        begin
            performTest(32'h00000010, 32'h00000002, OP_DIVIDE);
            performTest(32'hFFFFFFFF, 32'h00000001, OP_DIVIDE);
            performTest(32'h00000009, 32'h00000003, OP_DIVIDE);
            performTest(32'h00000008, 32'h00000002, OP_DIVIDE);
            performTest(32'h00000007, 32'h00000001, OP_DIVIDE);
            performTest(32'h12345678, 32'h00000002, OP_DIVIDE);
            performTest(32'hFFFFFFFF, 32'h00000000, OP_DIVIDE); // Dzielenie przez zero
            performTest(32'h00000001, 32'hFFFFFFFF, OP_DIVIDE);
        end
    endtask

    // Testy dla OP_ZM_TO_U2
    task perform_zm_to_u2_tests;
        begin
            performTest(32'h80000000, 0, OP_ZM_TO_U2);
            performTest(32'h7FFFFFFF, 0, OP_ZM_TO_U2);
            performTest(32'h80000001, 0, OP_ZM_TO_U2);
            performTest(32'h7FFFFFFE, 0, OP_ZM_TO_U2);
            performTest(32'h80000002, 0, OP_ZM_TO_U2);
            performTest(32'h00000001, 0, OP_ZM_TO_U2);
            performTest(32'hFFFFFFFF, 0, OP_ZM_TO_U2);
        end
    endtask

    // Testy flag statusu
    task perform_flag_status;
        begin
            performTest(32'h80000000, 32'h00000001, OP_DIVIDE); // Możliwy overflow
            performTest(32'h00000000, 32'h80000000, OP_COMPARE_AS); // Test flagi ZEROS
        end
    endtask

    task performTest;
        input [M-1:0] argA, argB;
        input [3:0] op;
        begin
            iarg_A <= argA;
            iarg_B <= argB;
            iop <= op;
            #20;
            display_results();
        end
    endtask

    task display_results;
        $display("Time: %t, Operation: %b, A: %b, B: %b, Result: %b, Status: %b", 
                 $time, iop, iarg_A, iarg_B, o_result, o_status);
    endtask

endmodule

waveform.vcd
$date
	Mon Dec 18 19:51:24 2023
$end
$version
	Icarus Verilog
$end
$timescale
	1ps
$end
$scope module test_sync_arith_unit_29 $end
$var wire 4 ! o_status [3:0] $end
$var wire 32 " o_result [31:0] $end
$var parameter 32 # M $end
$var parameter 4 $ OP_BITWISE_SHIFT $end
$var parameter 4 % OP_COMPARE_AS $end
$var parameter 4 & OP_DIVIDE $end
$var parameter 4 ' OP_ZM_TO_U2 $end
$var reg 1 ( clk $end
$var reg 1 ) i_reset $end
$var reg 32 * iarg_A [31:0] $end
$var reg 32 + iarg_B [31:0] $end
$var reg 4 , iop [3:0] $end
$var reg 32 - time_counter [31:0] $end
$var reg 32 . time_limit [31:0] $end
$scope module uut $end
$var wire 1 ( clk $end
$var wire 1 ) i_reset $end
$var wire 32 / iarg_A [31:0] $end
$var wire 32 0 iarg_B [31:0] $end
$var wire 4 1 iop [3:0] $end
$var wire 32 2 remainder [31:0] $end
$var wire 32 3 quotient [31:0] $end
$var wire 1 4 division_error $end
$var parameter 32 5 ERROR $end
$var parameter 32 6 M $end
$var parameter 32 7 NOT_EVEN_1 $end
$var parameter 4 8 OP_BITWISE_SHIFT $end
$var parameter 4 9 OP_COMPARE_AS $end
$var parameter 4 : OP_DIVIDE $end
$var parameter 4 ; OP_ZM_TO_U2 $end
$var parameter 32 < OVERFLOW $end
$var parameter 32 = ZEROS $end
$var reg 32 > o_result [31:0] $end
$var reg 4 ? o_status [3:0] $end
$scope module div_unit $end
$var wire 32 @ A [31:0] $end
$var wire 32 A B [31:0] $end
$var parameter 32 B M $end
$var reg 1 4 error $end
$var reg 32 C negated_B [31:0] $end
$var reg 32 D quotient [31:0] $end
$var reg 32 E remainder [31:0] $end
$var reg 32 F temp_remainder [31:0] $end
$var integer 32 G i [31:0] $end
$upscope $end
$upscope $end
$scope task display_results $end
$upscope $end
$scope task performTest $end
$var reg 32 H argA [31:0] $end
$var reg 32 I argB [31:0] $end
$var reg 4 J op [3:0] $end
$upscope $end
$scope task perform_compare_as_tests $end
$upscope $end
$scope task perform_divide_tests $end
$upscope $end
$scope task perform_flag_status $end
$upscope $end
$scope task perform_shift_tests $end
$upscope $end
$scope task perform_zm_to_u2_tests $end
$upscope $end
$upscope $end
$enddefinitions $end
$comment Show the parameter values. $end
$dumpall
b100000 B
b1 =
b0 <
b11 ;
b10 :
b1 9
b0 8
b10 7
b100000 6
b11 5
b11 '
b10 &
b1 %
b0 $
b100000 #
$end
#0
$dumpvars
bx J
bx I
bx H
bx G
bx F
bx E
bx D
bx C
bx A
bx @
b0 ?
b0 >
x4
bx 3
bx 2
bx 1
bx 0
bx /
b1111101000 .
b0 -
bx ,
bx +
bx *
0)
0(
b0 "
b0 !
$end
#5000
b101 -
#10000
b1010 -
1(
#15000
b1111 -
#20000
b10100 -
0(
1)
#25000
b11001 -
#30000
b1010 !
b1010 ?
b11110 -
1(
#35000
b100011 -
#40000
b0 C
b11111111111111111111111111111111 A
bx 2
bx E
b11111111111111111111111111111111 G
14
b0 F
bx 3
bx D
b0 ,
b0 1
b0 +
b0 0
b10100101101001011010010110100101 *
b10100101101001011010010110100101 /
b10100101101001011010010110100101 @
b101000 -
0(
b0 J
b0 I
b10100101101001011010010110100101 H
#45000
b101101 -
#50000
b10100101101001011010010110100101 "
b10100101101001011010010110100101 >
b10 !
b10 ?
b110010 -
1(
#55000
b110111 -
#60000
b0 2
b0 E
b0 F
b11111111111111111111111111111111 G
04
b10100101101001011010010110100101 3
b10100101101001011010010110100101 D
b1 C
b11111111111111111111111111111110 A
b1 +
b1 0
b111100 -
0(
b1 I
#65000
b1000001 -
#70000
b1010010110100101101001011010010 "
b1010010110100101101001011010010 >
b0 !
b0 ?
b1000110 -
1(
#75000
b1001011 -
#80000
b1 2
b1 E
b1 F
b11111111111111111111111111111111 G
b1010010110100101101001011010010 3
b1010010110100101101001011010010 D
b10 C
b11111111111111111111111111111101 A
b10 +
b10 0
b1010000 -
0(
b10 I
#85000
b1010101 -
#90000
b100 !
b100 ?
b101001011010010110100101101001 "
b101001011010010110100101101001 >
b1011010 -
1(
#95000
b1011111 -
#100000
b0 2
b0 E
b11111111111111111111111111111111 G
b0 F
b110111001101110011011100110111 3
b110111001101110011011100110111 D
b11 C
b11111111111111111111111111111100 A
b11 +
b11 0
b1100100 -
0(
b11 I
#105000
b1101001 -
#110000
b10100101101001011010010110100 "
b10100101101001011010010110100 >
b100 !
b100 ?
b1101110 -
1(
#115000
b1110011 -
#120000
b1 2
b1 E
b1 F
b11111111111111111111111111111111 G
b101001011010010110100101101001 3
b101001011010010110100101101001 D
b100 C
b11111111111111111111111111111011 A
b100 +
b100 0
b1111000 -
0(
b100 I
#125000
b1111101 -
#130000
b1010010110100101101001011010 "
b1010010110100101101001011010 >
b0 !
b0 ?
b10000010 -
1(
#135000
b10000111 -
#140000
b10110 2
b10110 E
b11111111111111111111111111111111 G
b10110 F
b101010101111110110010010001 3
b101010101111110110010010001 D
b11111 C
b11111111111111111111111111100000 A
b11111 +
b11111 0
b10001100 -
0(
b11111 I
#145000
b10010001 -
#150000
b1 "
b1 >
b10010110 -
1(
#155000
b10011011 -
#160000
b101 2
b101 E
b11111111111111111111111111111111 G
b101 F
b101001011010010110100101101 3
b101001011010010110100101101 D
b100000 C
b11111111111111111111111111011111 A
b100000 +
b100000 0
b10100000 -
0(
b100000 I
#165000
b10100101 -
#170000
b101 !
b101 ?
b0 "
b0 >
b10101010 -
1(
#175000
b10101111 -
#180000
b0 2
b0 E
b11111111111111111111111111111111 G
b0 F
b101000001010000010100000101 3
b101000001010000010100000101 D
b100001 C
b11111111111111111111111111011110 A
b100001 +
b100001 0
b10110100 -
0(
b100001 I
#185000
b10111001 -
#190000
b11 !
b11 ?
b10111110 -
1(
#195000
b11000011 -
#200000
b11111111111111111111111111111111 C
b0 A
b1 2
b1 E
b1 F
b11111111111111111111111111111111 G
b0 3
b0 D
b1 ,
b1 1
b11111111111111111111111111111111 +
b11111111111111111111111111111111 0
b1 *
b1 /
b1 @
b11001000 -
0(
b1 J
b11111111111111111111111111111111 I
b1 H
#205000
b11001101 -
#210000
b1 "
b1 >
b10 !
b10 ?
b11010010 -
1(
#215000
b11010111 -
#220000
b11111111111111111111111111111110 C
b1 A
b10 2
b10 E
b11111111111111111111111111111111 G
b10 F
b11111111111111111111111111111110 +
b11111111111111111111111111111110 0
b10 *
b10 /
b10 @
b11011100 -
0(
b11111111111111111111111111111110 I
b10 H
#225000
b11100001 -
#230000
b100 !
b100 ?
b11100110 -
1(
#235000
b11101011 -
#240000
b11111111111111111111111111111101 C
b10 A
b11 2
b11 E
b11111111111111111111111111111111 G
b11 F
b11111111111111111111111111111101 +
b11111111111111111111111111111101 0
b11 *
b11 /
b11 @
b11110000 -
0(
b11111111111111111111111111111101 I
b11 H
#245000
b11110101 -
#250000
b100 !
b100 ?
b11111010 -
1(
#255000
b11111111 -
#260000
b11111111111111111111111111111100 C
b11 A
b100 2
b100 E
b11111111111111111111111111111111 G
b100 F
b11111111111111111111111111111100 +
b11111111111111111111111111111100 0
b100 *
b100 /
b100 @
b100000100 -
0(
b11111111111111111111111111111100 I
b100 H
#265000
b100001001 -
#270000
b100 !
b100 ?
b100001110 -
1(
#275000
b100010011 -
#280000
b11111111111111111111111111111011 C
b100 A
b101 2
b101 E
b11111111111111111111111111111111 G
b101 F
b11111111111111111111111111111011 +
b11111111111111111111111111111011 0
b101 *
b101 /
b101 @
b100011000 -
0(
b11111111111111111111111111111011 I
b101 H
#285000
b100011101 -
#290000
b100 !
b100 ?
b100100010 -
1(
#295000
b100100111 -
#300000
b10000000000000000000000000000000 C
b1111111111111111111111111111111 A
b1111111111111111111111111111111 2
b1111111111111111111111111111111 E
b11111111111111111111111111111111 G
b1111111111111111111111111111111 F
b10000000000000000000000000000000 +
b10000000000000000000000000000000 0
b1111111111111111111111111111111 *
b1111111111111111111111111111111 /
b1111111111111111111111111111111 @
b100101100 -
0(
b10000000000000000000000000000000 I
b1111111111111111111111111111111 H
#305000
b100110001 -
#310000
b100 !
b100 ?
b100110110 -
1(
#315000
b100111011 -
#320000
b1 2
b1 E
b1111111111111111111111111111111 C
b10000000000000000000000000000000 A
b10 3
b10 D
b11111111111111111111111111111111 G
b1 F
b1111111111111111111111111111111 +
b1111111111111111111111111111111 0
b11111111111111111111111111111111 *
b11111111111111111111111111111111 /
b11111111111111111111111111111111 @
b101000000 -
0(
b1111111111111111111111111111111 I
b11111111111111111111111111111111 H
#325000
b101000101 -
#330000
b0 "
b0 >
b100 !
b100 ?
b101001010 -
1(
#335000
b101001111 -
#340000
b10 C
b11111111111111111111111111111101 A
b0 2
b0 E
b11111111111111111111111111111111 G
b0 F
b1000 3
b1000 D
b10 ,
b10 1
b10 +
b10 0
b10000 *
b10000 /
b10000 @
b101010100 -
0(
b10 J
b10 I
b10000 H
#345000
b101011001 -
#350000
b1000 "
b1000 >
b10 !
b10 ?
b101011110 -
1(
#355000
b101100011 -
#360000
b1 C
b11111111111111111111111111111110 A
b0 2
b0 E
b0 F
b11111111111111111111111111111111 G
b11111111111111111111111111111111 3
b11111111111111111111111111111111 D
b1 +
b1 0
b11111111111111111111111111111111 *
b11111111111111111111111111111111 /
b11111111111111111111111111111111 @
b101101000 -
0(
b1 I
b11111111111111111111111111111111 H
#365000
b101101101 -
#370000
b11111111111111111111111111111111 "
b11111111111111111111111111111111 >
b100 !
b100 ?
b101110010 -
1(
#375000
b101110111 -
#380000
b11 C
b11111111111111111111111111111100 A
b0 F
b11111111111111111111111111111111 G
b11 3
b11 D
b11 +
b11 0
b1001 *
b1001 /
b1001 @
b101111100 -
0(
b11 I
b1001 H
#385000
b110000001 -
#390000
b11 "
b11 >
b0 !
b0 ?
b110000110 -
1(
#395000
b110001011 -
#400000
b10 C
b11111111111111111111111111111101 A
b0 2
b0 E
b0 F
b11111111111111111111111111111111 G
b100 3
b100 D
b10 +
b10 0
b1000 *
b1000 /
b1000 @
b110010000 -
0(
b10 I
b1000 H
#405000
b110010101 -
#410000
b100 "
b100 >
b110011010 -
1(
#415000
b110011111 -
#420000
b1 C
b11111111111111111111111111111110 A
b0 2
b0 E
b0 F
b11111111111111111111111111111111 G
b111 3
b111 D
b1 +
b1 0
b111 *
b111 /
b111 @
b110100100 -
0(
b1 I
b111 H
#425000
b110101001 -
#430000
b100 !
b100 ?
b111 "
b111 >
b110101110 -
1(
#435000
b110110011 -
#440000
b10 C
b11111111111111111111111111111101 A
b0 F
b11111111111111111111111111111111 G
b1001000110100010101100111100 3
b1001000110100010101100111100 D
b10 +
b10 0
b10010001101000101011001111000 *
b10010001101000101011001111000 /
b10010001101000101011001111000 @
b110111000 -
0(
b10 I
b10010001101000101011001111000 H
#445000
b110111101 -
#450000
b1001000110100010101100111100 "
b1001000110100010101100111100 >
b100 !
b100 ?
b111000010 -
1(
#455000
b111000111 -
#460000
14
b0 C
b11111111111111111111111111111111 A
bx 2
bx E
b0 F
b11111111111111111111111111111111 G
bx 3
bx D
b0 +
b0 0
b11111111111111111111111111111111 *
b11111111111111111111111111111111 /
b11111111111111111111111111111111 @
b111001100 -
0(
b0 I
b11111111111111111111111111111111 H
#465000
b111010001 -
#470000
bx "
bx >
b1100 !
b1100 ?
b111010110 -
1(
#475000
b111011011 -
#480000
b1 2
b1 E
b1 F
b11111111111111111111111111111111 G
b11111111111111111111111111111111 C
b0 A
04
b0 3
b0 D
b11111111111111111111111111111111 +
b11111111111111111111111111111111 0
b1 *
b1 /
b1 @
b111100000 -
0(
b11111111111111111111111111111111 I
b1 H
#485000
b111100101 -
#490000
b0 "
b0 >
b0x0 !
b0x0 ?
b111101010 -
1(
#495000
b111101111 -
#500000
bx 3
bx D
14
b0 C
b11111111111111111111111111111111 A
bx 2
bx E
b11111111111111111111111111111111 G
b0 F
b11 ,
b11 1
b0 +
b0 0
b10000000000000000000000000000000 *
b10000000000000000000000000000000 /
b10000000000000000000000000000000 @
b111110100 -
0(
b11 J
b0 I
b10000000000000000000000000000000 H
#505000
b111111001 -
#510000
bx "
bx >
b1010 !
b1010 ?
b111111110 -
1(
#515000
b1000000011 -
#520000
14
bx 3
bx D
b1111111111111111111111111111111 *
b1111111111111111111111111111111 /
b1111111111111111111111111111111 @
b1000001000 -
0(
b1111111111111111111111111111111 H
#525000
b1000001101 -
#530000
b1111111111111111111111111111111 "
b1111111111111111111111111111111 >
b0x0 !
b0x0 ?
b1000010010 -
1(
#535000
b1000010111 -
#540000
14
bx 3
bx D
b10000000000000000000000000000001 *
b10000000000000000000000000000001 /
b10000000000000000000000000000001 @
b1000011100 -
0(
b10000000000000000000000000000001 H
#545000
b1000100001 -
#550000
b11111111111111111111111111111111 "
b11111111111111111111111111111111 >
b100 !
b100 ?
b1000100110 -
1(
#555000
b1000101011 -
#560000
14
bx 3
bx D
b1111111111111111111111111111110 *
b1111111111111111111111111111110 /
b1111111111111111111111111111110 @
b1000110000 -
0(
b1111111111111111111111111111110 H
#565000
b1000110101 -
#570000
b1111111111111111111111111111110 "
b1111111111111111111111111111110 >
b0 !
b0 ?
b1000111010 -
1(
#575000
b1000111111 -
#580000
14
bx 3
bx D
b10000000000000000000000000000010 *
b10000000000000000000000000000010 /
b10000000000000000000000000000010 @
b1001000100 -
0(
b10000000000000000000000000000010 H
#585000
b1001001001 -
#590000
b11111111111111111111111111111110 "
b11111111111111111111111111111110 >
b1001001110 -
1(
#595000
b1001010011 -
#600000
14
bx 3
bx D
b1 *
b1 /
b1 @
b1001011000 -
0(
b1 H
#605000
b1001011101 -
#610000
b100 !
b100 ?
b1 "
b1 >
b1001100010 -
1(
#615000
b1001100111 -
#620000
14
bx 3
bx D
b11111111111111111111111111111111 *
b11111111111111111111111111111111 /
b11111111111111111111111111111111 @
b1001101100 -
0(
b11111111111111111111111111111111 H
#625000
b1001110001 -
#630000
b10000000000000000000000000000001 "
b10000000000000000000000000000001 >
b100 !
b100 ?
b1001110110 -
1(
#635000
b1001111011 -
#640000
b0 2
b0 E
b0 F
b11111111111111111111111111111111 G
b1 C
b11111111111111111111111111111110 A
04
b10000000000000000000000000000000 3
b10000000000000000000000000000000 D
b10 ,
b10 1
b1 +
b1 0
b10000000000000000000000000000000 *
b10000000000000000000000000000000 /
b10000000000000000000000000000000 @
b1010000000 -
0(
b10 J
b1 I
b10000000000000000000000000000000 H
#645000
b1010000101 -
#650000
b10000000000000000000000000000000 "
b10000000000000000000000000000000 >
b0 !
b0 ?
b1010001010 -
1(
#655000
b1010001111 -
#660000
b10000000000000000000000000000000 C
b1111111111111111111111111111111 A
b11111111111111111111111111111111 G
b0 3
b0 D
b1 ,
b1 1
b10000000000000000000000000000000 +
b10000000000000000000000000000000 0
b0 *
b0 /
b0 @
b1010010100 -
0(
b1 J
b10000000000000000000000000000000 I
b0 H
#665000
b1010011001 -
#670000
b100 !
b100 ?
b1 "
b1 >
b1010011110 -
1(
#675000
b1010100011 -
#680000
b1010101000 -
0(
