sync_arith_unit_29.sv
// Module sync_arith_unit_29: A Synchronous Arithmetic and Logic Unit
module sync_arith_unit_29 #(parameter M = 32) (
    input wire [M-1:0] iarg_A,    // Input argument A, M-bit wide
    input wire [M-1:0] iarg_B,    // Input argument B, M-bit wide
    input wire [3:0] iop,         // Operation code input, 4-bit wide
    input wire clk,               // Clock input
    input wire i_reset,           // Synchronous reset input
    output reg [M-1:0] o_result,  // Output result, M-bit wide
    output reg [3:0] o_status     // Output status, 4-bit wide
);

// Status flags definitions
localparam ERROR = 3;        // Error flag
localparam NOT_EVEN_1 = 2;   // Flag for odd number of ones in the result
localparam ZEROS = 1;        // Flag indicating all zeros in the result
localparam OVERFLOW = 0;     // Overflow flag

// ALU logic implementation
always @(posedge clk or negedge i_reset) begin
    if (!i_reset) begin
        // Resetting the module
        o_result <= 0;
        o_status <= 0;
    end else begin
        // Resetting the status at the start of each cycle
        o_status <= 0;

        case (iop)
            4'b0000: begin // Operation A<~B (Bitwise Right Shift)
                if (~iarg_B < 0) begin
                    o_status[ERROR] <= 1'b1;
                    o_result <= {M{1'bx}}; // Undefined value
                end else begin
                    o_result <= iarg_A >> ~iarg_B;
                end
            end
            4'b0001: begin // Operation AS~B (Check if A <= ~B)
                o_result <= (iarg_A <= ~iarg_B) ? {M{1'b1}} : {M{1'b0}};
            end
            4'b0010: begin // Operation A/B (Division)
                if (iarg_B == 0) begin
                    o_status[ERROR] <= 1'b1;
                    o_result <= {M{1'bx}};
                end else begin
                    o_result <= $signed(iarg_A) / $signed(iarg_B);
                end
            end
            4'b0011: begin // Operation ZM(A) => U2(A) (Code Conversion)
                // Assuming the MSB of iarg_A is the sign bit
                if (iarg_A[M-1] == 1'b0) begin // Positive number
                    o_result <= iarg_A;
                end else begin // Negative number
                    o_result <= (~iarg_A + 1'b1) | (1'b1 << (M-1)); // Convert to Two's Complement
                end
            end
            default: begin
                o_status[ERROR] <= 1'b1; // Unknown operation
            end
        endcase
    end
end

endmodule

sync_arith_unit_29_tb.sv
`include "sync_arith_unit_29.sv"

`timescale 1ns / 1ps

module sync_arith_unit_29_tb;

parameter M = 32;
reg [M-1:0] iarg_A, iarg_B;
reg [3:0] iop;
reg clk, i_reset;
wire [M-1:0] o_result;
wire [3:0] o_status;

sync_arith_unit_29 #(.M(M)) UUT (
    .iarg_A(iarg_A),
    .iarg_B(iarg_B),
    .iop(iop),
    .clk(clk),
    .i_reset(i_reset),
    .o_result(o_result),
    .o_status(o_status)
);

initial begin
    // Initialization
    $dumpfile("waveform.vcd");
    $dumpvars(0, sync_arith_unit_29_tb);
    clk = 0;
    i_reset = 1;
    iarg_A = 0;
    iarg_B = 0;
    iop = 0;

    // Reset
    #10;
    i_reset = 0;
    #10;
    i_reset = 1;
    #10;

    // Test Cases
    // Test Case 1: Bitwise Right Shift
    iarg_A = 15; iarg_B = 3; iop = 4'b0000;
    #20;

    // Test Case 2: Check if A <= ~B
    iarg_A = 10; iarg_B = 5; iop = 4'b0001;
    #20;

    // Test Case 3: Division A / ~B
    iarg_A = 20; iarg_B = 4; iop = 4'b0010;
    #20;

    // Test Case 4: Conversion ZM(A) => U2(A)
    iarg_A = 8'b10000001; iop = 4'b0011;
    #20;

    #100; // Wait for some time to observe the results
    $finish; // Finish simulation
end

// Generating a clock signal
always #5 clk = ~clk;

// Monitor values
initial begin
    $monitor("Time = %t, iarg_A = %d, iarg_B = %d, iop = %b, o_result = %d, o_status = %b",
             $time, iarg_A, iarg_B, iop, o_result, o_status);
end

endmodule

waveform.vcd
$date
	Tue Dec  5 21:41:38 2023
$end
$version
	Icarus Verilog
$end
$timescale
	1ps
$end
$scope module sync_arith_unit_29_tb $end
$var wire 4 ! o_status [3:0] $end
$var wire 32 " o_result [31:0] $end
$var parameter 32 # M $end
$var reg 1 $ clk $end
$var reg 1 % i_reset $end
$var reg 32 & iarg_A [31:0] $end
$var reg 32 ' iarg_B [31:0] $end
$var reg 4 ( iop [3:0] $end
$scope module UUT $end
$var wire 1 $ clk $end
$var wire 1 % i_reset $end
$var wire 32 ) iarg_A [31:0] $end
$var wire 32 * iarg_B [31:0] $end
$var wire 4 + iop [3:0] $end
$var parameter 32 , ERROR $end
$var parameter 32 - M $end
$var parameter 32 . NOT_EVEN_1 $end
$var parameter 32 / OVERFLOW $end
$var parameter 32 0 ZEROS $end
$var reg 32 1 o_result [31:0] $end
$var reg 4 2 o_status [3:0] $end
$upscope $end
$upscope $end
$enddefinitions $end
$comment Show the parameter values. $end
$dumpall
b1 0
b0 /
b10 .
b100000 -
b11 ,
b100000 #
$end
#0
$dumpvars
bx 2
bx 1
b0 +
b0 *
b0 )
b0 (
b0 '
b0 &
1%
0$
bx "
bx !
$end
#5000
b0 "
b0 1
b0 !
b0 2
1$
#10000
0$
0%
#15000
1$
#20000
0$
1%
#25000
1$
#30000
0$
b11 '
b11 *
b1111 &
b1111 )
#35000
1$
#40000
0$
#45000
1$
#50000
0$
b1 (
b1 +
b101 '
b101 *
b1010 &
b1010 )
#55000
b11111111111111111111111111111111 "
b11111111111111111111111111111111 1
1$
#60000
0$
#65000
1$
#70000
0$
b10 (
b10 +
b100 '
b100 *
b10100 &
b10100 )
#75000
b101 "
b101 1
1$
#80000
0$
#85000
1$
#90000
0$
b11 (
b11 +
b10000001 &
b10000001 )
#95000
b10000001 "
b10000001 1
1$
